aioghost/__init__.py
aioghost/client.py
aioghost/exceptions.py
aioghost-0.2.0.dist-info/METADATA
aioghost-0.2.0.dist-info/WHEEL
aioghost-0.2.0.dist-info/licenses/LICENSE
aioghost-0.2.0.dist-info/RECORD
