Metadata-Version: 2.4
Name: aioghost
Version: 0.2.0
Summary: Async Python client for the Ghost Admin API
Project-URL: Homepage, https://github.com/vitrixbot/aioghost
Project-URL: Documentation, https://github.com/vitrixbot/aioghost#readme
Project-URL: Repository, https://github.com/vitrixbot/aioghost
Project-URL: Issues, https://github.com/vitrixbot/aioghost/issues
Author-email: vitrixbot <vitrixclawd@icloud.com>
License-Expression: MIT
License-File: LICENSE
Keywords: aiohttp,api,async,asyncio,cms,ghost
Classifier: Development Status :: 4 - Beta
Classifier: Framework :: AsyncIO
Classifier: Intended Audience :: Developers
Classifier: License :: OSI Approved :: MIT License
Classifier: Operating System :: OS Independent
Classifier: Programming Language :: Python :: 3
Classifier: Programming Language :: Python :: 3.11
Classifier: Programming Language :: Python :: 3.12
Classifier: Topic :: Internet :: WWW/HTTP
Requires-Python: >=3.11
Requires-Dist: aiohttp>=3.8.0
Requires-Dist: pyjwt>=2.0.0
Provides-Extra: dev
Requires-Dist: aioresponses>=0.7.0; extra == 'dev'
Requires-Dist: mypy>=1.0.0; extra == 'dev'
Requires-Dist: pytest-aiohttp>=1.0.0; extra == 'dev'
Requires-Dist: pytest-asyncio>=0.21.0; extra == 'dev'
Requires-Dist: pytest>=7.0.0; extra == 'dev'
Requires-Dist: ruff>=0.1.0; extra == 'dev'
